read5_ont/AbstractFileReader.py
read5_ont/Exceptions.py
read5_ont/Fast5Reader.py
read5_ont/Pod5Reader.py
read5_ont/Reader.py
read5_ont/__init__.py
read5_ont/_version.py
read5_ont-1.2.8.dist-info/METADATA
read5_ont-1.2.8.dist-info/WHEEL
read5_ont-1.2.8.dist-info/licenses/LICENSE
read5_ont-1.2.8.dist-info/RECORD
