Metadata-Version: 2.4
Name: read5_ont
Version: 1.2.8
Summary: Wrapper to read fast5 and pod5 files.
Project-URL: repository, https://github.com/rnajena/read5_ont
Author-email: Jannes Spangenberg <jannes.spangenberg@uni-jena.de>
License: GNUv3
License-File: LICENSE
Classifier: Development Status :: 5 - Production/Stable
Classifier: Intended Audience :: Developers
Classifier: Intended Audience :: Science/Research
Classifier: License :: OSI Approved :: GNU General Public License v3 (GPLv3)
Classifier: Programming Language :: Python
Classifier: Programming Language :: Python :: 3 :: Only
Classifier: Programming Language :: Python :: 3.10
Classifier: Programming Language :: Python :: 3.11
Classifier: Programming Language :: Python :: 3.12
Classifier: Topic :: Scientific/Engineering :: Bio-Informatics
Requires-Python: >=3.10
Requires-Dist: h5py>=3.0
Requires-Dist: numpy>=1.20
Requires-Dist: pod5>=0.3.23
Requires-Dist: vbz-h5py-plugin>=1.0.1
Provides-Extra: test
Requires-Dist: mypy; extra == 'test'
Requires-Dist: pytest; extra == 'test'
Requires-Dist: pytest-cov; extra == 'test'
